{
  "ca": {
    "revision": "3e911ef81869",
    "platforms": ["android"]
  },
  "cs": {
    "revision": "9caef02df392",
    "platforms": ["android", "android-multilocale"]
  },
  "da": {
    "revision": "6104b018b80e",
    "platforms": ["android", "android-multilocale"]
  },
  "de": {
    "revision": "5eb2fb1a7155",
    "platforms": ["android", "android-multilocale"]
  },
  "es-AR": {
    "revision": "e01015859441",
    "platforms": ["android"]
  },
  "es-ES": {
    "revision": "34e0d8e1e116",
    "platforms": ["android", "android-multilocale"]
  },
  "fi": {
    "revision": "6251619681a4",
    "platforms": ["android", "android-multilocale"]
  },
  "fr": {
    "revision": "f67b5f685d22",
    "platforms": ["android", "android-multilocale"]
  },
  "fy-NL": {
    "revision": "835d6bd17cc3",
    "platforms": ["android"]
  },
  "ga-IE": {
    "revision": "b611f1be732c",
    "platforms": ["android"]
  },
  "gl": {
    "revision": "6a40cee822a6",
    "platforms": ["android"]
  },
  "it": {
    "revision": "69284ea2c066",
    "platforms": ["android", "android-multilocale"]
  },
  "ja": {
    "revision": "22de89d48112",
    "platforms": ["android", "android-multilocale"]
  },
  "ko": {
    "revision": "5acebc6c43a5",
    "platforms": ["android", "android-multilocale"]
  },
  "lt": {
    "revision": "60a94ba9301b",
    "platforms": ["android"]
  },
  "nb-NO": {
    "revision": "35839a743075",
    "platforms": ["android", "android-multilocale"]
  },
  "nl": {
    "revision": "34622ae777fc",
    "platforms": ["android", "android-multilocale"]
  },
  "pa-IN": {
    "revision": "4afbb88e0ccf",
    "platforms": ["android"]
  },
  "pl": {
    "revision": "068c2c944a6b",
    "platforms": ["android", "android-multilocale"]
  },
  "pt-BR": {
    "revision": "7f9c10c6fa75",
    "platforms": ["android", "android-multilocale"]
  },
  "pt-PT": {
    "revision": "bda797d0c910",
    "platforms": ["android", "android-multilocale"]
  },
  "ru": {
    "revision": "79b4f720a90a",
    "platforms": ["android", "android-multilocale"]
  },
  "sk": {
    "revision": "5c2dc048372d",
    "platforms": ["android"]
  },
  "sl": {
    "revision": "07442918d3aa",
    "platforms": ["android"]
  },
  "uk": {
    "revision": "e54754531f14",
    "platforms": ["android"]
  },
  "zh-CN": {
    "revision": "f9cbb1732186",
    "platforms": ["android"]
  },
  "zh-TW": {
    "revision": "9d71fa0a092f",
    "platforms": ["android"]
  }
}
